fgread/__init__.py
fgread/helpers.py
fgread/read.py
fgread/readers.py
fgread-0.7.7.dist-info/LICENSE
fgread-0.7.7.dist-info/WHEEL
fgread-0.7.7.dist-info/METADATA
fgread-0.7.7.dist-info/RECORD
