Metadata-Version: 2.1
Name: fgread
Version: 0.7.7
Summary: Module for reading datasets shared on FASTGenomics
Home-page: https://github.com/FASTGenomics/fgread-py
Author: FASTGenomics Team
Author-email: contact@fastgenomics.org
Requires-Python: ~=3.6
Classifier: Development Status :: 5 - Production/Stable
Classifier: Intended Audience :: Science/Research
Classifier: License :: OSI Approved :: MIT License
Classifier: Programming Language :: Python :: 3
Classifier: Topic :: Scientific/Engineering :: Bio-Informatics
Requires-Dist: anndata ~= 0.6
Requires-Dist: get_version
Requires-Dist: tables ~= 3.6
Requires-Dist: loompy ~= 3.0
Requires-Dist: scanpy ~= 1.4
Requires-Dist: pandas >= 0.25
Requires-Dist: pytest >= 4 ; extra == "test"
Project-URL: Documentation, https://fgread-py.readthedocs.io/en/stable/
Provides-Extra: test
